spdr/__init__.py
spdr/spdr.py
spdr/fetcher/__init__.py
spdr/fetcher/fetcher.py
spdr/stack/__init__.py
spdr/stack/stack.py
spdr/writer/__init__.py
spdr/writer/writer.py
tests/__init__.py
tests/fetcher/__init__.py
tests/fetcher/test_fetcher.py
tests/stack/__init__.py
tests/stack/test_stack.py
tests/writer/__init__.py
tests/writer/test_writer.py
spdr-0.0.0.dist-info/METADATA
spdr-0.0.0.dist-info/WHEEL
spdr-0.0.0.dist-info/top_level.txt
spdr-0.0.0.dist-info/RECORD
