Metadata-Version: 2.1
Name: spdr
Version: 0.0.0
Summary: Python library for crawling the Twitter user graph.
Home-page: UNKNOWN
Author: Davide Palmisano
Author-email: dpalmisano@gmail.com
License: MIT License
Platform: UNKNOWN
Requires-Dist: requests
Requires-Dist: ratelimit
